{
    "version": "3.0.0",
    "summary": "Slate Query Engine",
    "repository": "https://github.com/panosoft/slate-query-engine.git",
    "license": "Unlicense",
    "source-directories": [
        "src",
        "Test/"
    ],
    "exposed-modules": [
        "Slate.Engine.Engine",
        "Slate.Engine.Query"
    ],
    "native-modules": true,
    "dependencies": {
		"elm-lang/core": "5.0.0 <= v < 6.0.0",
		"elm-community/json-extra": "2.1.0 <= v < 3.0.0",
        "elm-community/list-extra": "6.0.0 <= v < 7.0.0",
        "elm-community/maybe-extra": "3.1.0 <= v < 4.0.0",
        "elm-community/result-extra": "2.2.0 <= v < 3.0.0",
		"panosoft/elm-string-utils": "2.0.0 <= v < 3.0.0",
		"panosoft/elm-postgres": "4.0.0 <= v < 5.0.0",
        "panosoft/elm-debugf": "2.0.0 <= v < 3.0.0",
        "panosoft/elm-parent-child-update": "2.0.0 <= v < 3.0.0",
        "panosoft/elm-string-utils": "2.0.0 <= v < 3.0.0",
        "panosoft/elm-utils": "2.0.0 <= v < 3.0.0",
        "panosoft/elm-cmd-retry": "3.0.0 <= v < 4.0.0",
        "panosoft/slate-common": "2.0.0 <= v < 3.0.0",
        "panosoft/slate-test-entities": "2.0.0 <= v < 3.0.0"
    },
    "elm-version": "0.18.0 <= v < 0.19.0"
}
